spilite/__init__.py
spilite/spi.py
spilite/cs/__init__.py
spilite/cs/decoders.py
spilite/cs/pins.py
spilite-0.1.4.dist-info/LICENSE
spilite-0.1.4.dist-info/METADATA
spilite-0.1.4.dist-info/WHEEL
spilite-0.1.4.dist-info/top_level.txt
spilite-0.1.4.dist-info/RECORD
