Metadata-Version: 2.1
Name: spilite
Version: 0.1.4
Summary: A lite wrapper for spidev with additional chip select options
Home-page: https://github.com/xdylanm/spilite
Author: xdylanm
License: UNKNOWN
Platform: UNKNOWN
Classifier: Programming Language :: Python :: 3
Classifier: Programming Language :: Python :: 3.6
Classifier: License :: OSI Approved :: MIT License
Classifier: Operating System :: OS Independent
Requires-Python: >=3.6
License-File: LICENSE
Requires-Dist: gpiozero
Requires-Dist: spidev
